django_loaddata/__init__.py
django_loaddata/apps.py
django_loaddata/models.py
django_loaddata/utils.py
django_loaddata/management/__init__.py
django_loaddata/management/commands/__init__.py
django_loaddata/management/commands/loaddata.py
django_loaddata/migrations/0001_initial.py
django_loaddata/migrations/__init__.py
django_loaddata-0.0.1.dist-info/LICENSE
django_loaddata-0.0.1.dist-info/METADATA
django_loaddata-0.0.1.dist-info/WHEEL
django_loaddata-0.0.1.dist-info/entry_points.txt
django_loaddata-0.0.1.dist-info/top_level.txt
django_loaddata-0.0.1.dist-info/RECORD
