Metadata-Version: 2.2
Name: django_loaddata
Version: 0.0.1
Summary: Extended django loaddata command for uploading fixtures
Home-page: https://github.com/Friskes/django-loaddata
Author: Friskes
Author-email: Friskes <friskesx@gmail.com>
License: MIT License
Project-URL: Homepage, https://github.com/Friskes/django-loaddata
Project-URL: Changelog, https://github.com/Friskes/django-loaddata/releases/
Project-URL: Issues, https://github.com/Friskes/django-loaddata/issues
Keywords: Django,Fixtures,Database,CLI
Classifier: Development Status :: 5 - Production/Stable
Classifier: Environment :: Web Environment
Classifier: Intended Audience :: Developers
Classifier: Operating System :: OS Independent
Classifier: License :: OSI Approved :: MIT License
Classifier: Programming Language :: Python :: 3.9
Classifier: Programming Language :: Python :: 3.10
Classifier: Programming Language :: Python :: 3.11
Classifier: Programming Language :: Python :: 3.12
Classifier: Framework :: Django :: 4.0
Classifier: Framework :: Django :: 4.1
Classifier: Framework :: Django :: 4.2
Classifier: Topic :: Internet :: WWW/HTTP
Classifier: Topic :: Documentation
Classifier: Topic :: Software Development :: Code Generators
Requires-Python: >=3.9
License-File: LICENSE
Requires-Dist: django>=4.0.0
Provides-Extra: dev
Requires-Dist: pre-commit>=3.5.0; extra == "dev"
Requires-Dist: ruff==0.8.0; extra == "dev"
Requires-Dist: mypy>=1.10.0; extra == "dev"
Requires-Dist: pytest>=7.0.1; extra == "dev"
Requires-Dist: pytest-cov>=5.0.0; extra == "dev"
Requires-Dist: pytest-django==4.9.0; extra == "dev"
Requires-Dist: django-test-migrations==1.4.0; extra == "dev"
Provides-Extra: ci
Requires-Dist: ruff==0.8.0; extra == "ci"
Requires-Dist: mypy>=1.10.0; extra == "ci"
Requires-Dist: pytest>=7.0.1; extra == "ci"
Requires-Dist: pytest-cov>=5.0.0; extra == "ci"
Requires-Dist: pytest-django==4.9.0; extra == "ci"
Requires-Dist: django-test-migrations==1.4.0; extra == "ci"
